bbee/__init__.py
bbee-0.1.0.dist-info/LICENSE
bbee-0.1.0.dist-info/METADATA
bbee-0.1.0.dist-info/WHEEL
bbee-0.1.0.dist-info/entry_points.txt
bbee-0.1.0.dist-info/top_level.txt
bbee-0.1.0.dist-info/RECORD
