Metadata-Version: 2.1
Name: bbee
Version: 0.1.0
Summary: A small C/C++ Builder
Home-page: https://github.com/sinanislekdemir/bbee
Author: Sinan Islekdemir
Author-email: sinan@islekdemir.com
License: UNKNOWN
Platform: UNKNOWN
Classifier: Programming Language :: Python :: 3
Classifier: License :: OSI Approved :: MIT License
Classifier: Operating System :: OS Independent
